agent_governance/__init__.py
agent_governance/agentctl.py
agent_governance/init.py
agent_governance/update_check.py
agent_governance/contracts/__init__.py
agent_governance/contracts/output_packet.schema.json
agent_governance/contracts/task_packet.schema.json
agent_governance-1.0.10.dist-info/METADATA
agent_governance-1.0.10.dist-info/WHEEL
agent_governance-1.0.10.dist-info/entry_points.txt
agent_governance-1.0.10.dist-info/top_level.txt
agent_governance-1.0.10.dist-info/RECORD
