Metadata-Version: 2.4
Name: agent-governance
Version: 1.0.10
Summary: Agent governance tooling
Requires-Python: >=3.10
Requires-Dist: pyyaml>=6.0
Requires-Dist: jsonschema>=4.21
Requires-Dist: packaging>=22
Requires-Dist: tomli>=2.0; python_version < "3.11"
